LICENSE
README.md
setup.py
funcspy.egg-info/PKG-INFO
funcspy.egg-info/SOURCES.txt
funcspy.egg-info/dependency_links.txt
funcspy.egg-info/requires.txt
funcspy.egg-info/top_level.txt
funcspy/emails_funcs/__init__.py
funcspy/emails_funcs/emails_funcs.py
funcspy/exceptions_funcs/__init__.py
funcspy/exceptions_funcs/exceptions_funcs.py
funcspy/gui_funcs/__init__.py
funcspy/gui_funcs/gui_funcs.py
funcspy/pdf_funcs/ocr_funcs/__init__.py
funcspy/pdf_funcs/ocr_funcs/orc.py
funcspy/pdf_funcs/pdfutils/__init__.py
funcspy/pdf_funcs/pdfutils/pdfutils.py
funcspy/python_funcs/__init__.py
funcspy/python_funcs/python_funcs.py
funcspy/regex_funcs/__init__.py
funcspy/regex_funcs/regex_funcs.py
funcspy/selenium_funcs/__init__.py
funcspy/selenium_funcs/selenium_funcs.py
funcspy/utils_funcs/__init__.py
funcspy/utils_funcs/utils_funcs.py