Metadata-Version: 2.1
Name: funcspy
Version: 1.1.1
Summary: Functions to help you develop any program or script you want
Home-page: https://github.com/gabriellopesdesouza2002/funcspy
Author: Gabriel Lopes de Souza
Author-email: gabriellopesdesouza2002@gmail.com
License: MIT License
Keywords: Functions to help you develop any program or script you want
License-File: LICENSE
